zae_cli/__init__.py
zae_cli/example_mpu_script.py
zae_cli/example_script.py
zae_cli/main.py
zae_cli/modules/__init__.py
zae_cli/modules/doctor.py
zae_cli/modules/tree_builder.py
zae_engine/__init__.py
zae_engine/data/README_dataset-ko.md
zae_engine/data/README_dataset.md
zae_engine/data/__init__.py
zae_engine/data/collate/__init__.py
zae_engine/data/collate/core.py
zae_engine/data/collate/modules.py
zae_engine/data/dataset/__init__.py
zae_engine/data/dataset/parquet.py
zae_engine/examples/__init__.py
zae_engine/examples/classification1D.py
zae_engine/examples/ddpm_mnist.py
zae_engine/examples/segmentation1D.py
zae_engine/loss/README_loss-ko.md
zae_engine/loss/README_loss.md
zae_engine/loss/__init__.py
zae_engine/loss/_loss.py
zae_engine/loss/angular.py
zae_engine/loss/iou.py
zae_engine/loss/norm.py
zae_engine/metrics/README_metrics-ko.md
zae_engine/metrics/README_metrics.md
zae_engine/metrics/__init__.py
zae_engine/metrics/bijective.py
zae_engine/metrics/confusion.py
zae_engine/metrics/count.py
zae_engine/metrics/iou.py
zae_engine/metrics/signals.py
zae_engine/models/README_models-ko.md
zae_engine/models/README_models.md
zae_engine/models/__init__.py
zae_engine/models/builds/__init__.py
zae_engine/models/builds/autoencoder.py
zae_engine/models/builds/cnn.py
zae_engine/models/builds/nested_autoencoder.py
zae_engine/models/builds/transformer.py
zae_engine/models/converter/__init__.py
zae_engine/models/converter/dim_converter.py
zae_engine/models/foundations/__init__.py
zae_engine/models/foundations/benchmark.py
zae_engine/models/foundations/bert.py
zae_engine/models/foundations/resnet.py
zae_engine/models/foundations/unet.py
zae_engine/models/foundations/word_embedding.py
zae_engine/models/utility.py
zae_engine/nn_night/README_blocks-ko.md
zae_engine/nn_night/README_blocks.md
zae_engine/nn_night/README_layers-ko.md
zae_engine/nn_night/README_layers.md
zae_engine/nn_night/__init__.py
zae_engine/nn_night/blocks/__init__.py
zae_engine/nn_night/blocks/conv_block.py
zae_engine-0.7.6.dist-info/LICENSE
zae_engine-0.7.6.dist-info/METADATA
zae_engine-0.7.6.dist-info/WHEEL
zae_engine-0.7.6.dist-info/entry_points.txt
zae_engine-0.7.6.dist-info/RECORD
