Metadata-Version: 2.3
Name: zae-engine
Version: 0.7.6
Summary: Deep learning engine powered by zae-park.
Author: zae-park
Author-email: tom941105@gmail.com
Requires-Python: >=3.10,<4.0
Classifier: Programming Language :: Python :: 3
Classifier: Programming Language :: Python :: 3.10
Classifier: Programming Language :: Python :: 3.11
Classifier: Programming Language :: Python :: 3.12
Classifier: Programming Language :: Python :: 3.13
Requires-Dist: click (>=8.1.7,<9.0.0)
Requires-Dist: nibabel (>=5.1.0,<6.0.0)
Requires-Dist: pandas (>=2.1.2,<3.0.0)
Requires-Dist: pillow (>=11.0.0,<12.0.0)
Requires-Dist: psutil (>=5.9.5,<6.0.0)
Requires-Dist: rich (>=13.5.2,<14.0.0)
Requires-Dist: tqdm (>=4.65.0,<5.0.0)
Requires-Dist: wfdb (>=4.1.2,<5.0.0)
